{
  "value": [
    {
      "id": "1767067945965facspp67z0",
      "spkNo": "SPK/251230/059DZ-A",
      "soNo": "TEST-0001",
      "customer": "PT.TEST 1",
      "product": "BOX MIE AYAM",
      "product_id": "FG-TEST-00001",
      "kode": "FG-TEST-00001",
      "qty": 500,
      "unit": "PCS",
      "status": "CLOSE",
      "created": "2025-12-30T04:12:25.965Z",
      "notes": "URGENT ",
      "originalSpkNo": "SPK/251230/059DZ",
      "batchNo": "A",
      "bomOverride": {
        "MTRL-00829": 520
      },
      "updated": "2025-12-30T04:20:34.449Z",
      "padCode": ""
    },
    {
      "id": "17670679459653p8hoy08d1",
      "spkNo": "SPK/251230/059DZ-B",
      "soNo": "TEST-0001",
      "customer": "PT.TEST 1",
      "product": "BOX MIE AYAM",
      "product_id": "FG-TEST-00001",
      "kode": "FG-TEST-00001",
      "qty": 500,
      "unit": "PCS",
      "status": "CLOSE",
      "created": "2025-12-30T04:12:25.965Z",
      "notes": "URGENT ",
      "originalSpkNo": "SPK/251230/059DZ",
      "batchNo": "B",
      "bomOverride": {
        "MTRL-00829": 520
      },
      "updated": "2025-12-30T04:19:33.033Z",
      "padCode": ""
    },
    {
      "id": "1767075207752r0vqyeovl",
      "spkNo": "SPK/251230/HW00G",
      "soNo": "TEST-0002",
      "customer": "PT.TEST 1",
      "product": "BOX TEST 1",
      "product_id": "FG-TEST-00002",
      "kode": "FG-TEST-00002",
      "qty": 500,
      "unit": "PCS",
      "status": "CLOSE",
      "created": "2025-12-30T06:13:27.752Z",
      "notes": "URGENT",
      "bomOverride": {
        "MTRL-00829": 510
      },
      "updated": "2025-12-30T06:16:52.943Z",
      "padCode": ""
    },
    {
      "id": "1767077532289835o3312y",
      "spkNo": "SPK/251230/8R22S",
      "soNo": "TEST-3",
      "customer": "PT.TEST 1",
      "product": "BOX MIE AYAM",
      "product_id": "FG-TEST-00001",
      "kode": "FG-TEST-00001",
      "qty": 800,
      "unit": "PCS",
      "status": "OPEN",
      "created": "2025-12-30T06:52:12.289Z",
      "notes": "",
      "stockFulfilled": true,
      "progress": 800,
      "padCode": ""
    },
    {
      "id": "17670776170357g7l02o5h0",
      "spkNo": "SPK/251230/400ZS-A",
      "soNo": "TEST-3",
      "customer": "PT.TEST 1",
      "product": "BOX TEST 1",
      "product_id": "FG-TEST-00002",
      "kode": "FG-TEST-00002",
      "qty": 200,
      "unit": "PCS",
      "status": "OPEN",
      "created": "2025-12-30T06:53:37.035Z",
      "notes": "",
      "originalSpkNo": "SPK/251230/400ZS",
      "batchNo": "A",
      "padCode": "",
      "stockFulfilled": true,
      "progress": 200
    },
    {
      "id": "1767077617035x6tg5w56i1",
      "spkNo": "SPK/251230/400ZS-B",
      "soNo": "TEST-3",
      "customer": "PT.TEST 1",
      "product": "BOX TEST 1",
      "product_id": "FG-TEST-00002",
      "kode": "FG-TEST-00002",
      "qty": 300,
      "unit": "PCS",
      "status": "OPEN",
      "created": "2025-12-30T06:53:37.035Z",
      "notes": "",
      "originalSpkNo": "SPK/251230/400ZS",
      "batchNo": "B",
      "padCode": "",
      "stockFulfilled": true,
      "progress": 300
    },
    {
      "id": "1767077617035jgmwywi672",
      "spkNo": "SPK/251230/400ZS-C",
      "soNo": "TEST-3",
      "customer": "PT.TEST 1",
      "product": "BOX TEST 1",
      "product_id": "FG-TEST-00002",
      "kode": "FG-TEST-00002",
      "qty": 300,
      "unit": "PCS",
      "status": "OPEN",
      "created": "2025-12-30T06:53:37.035Z",
      "notes": "",
      "originalSpkNo": "SPK/251230/400ZS",
      "batchNo": "C",
      "padCode": "",
      "stockFulfilled": true,
      "progress": 300
    },
    {
      "id": "1767078303551pvt9t5t2p",
      "spkNo": "SPK/251230/YNJ7V",
      "soNo": "Tes4",
      "customer": "PT. DWIKARYA SEJAHTERA",
      "product": "BOX LYSAGHT KL65 700X260X215 (K150/M125/KM150) (PRINTING HITAM)",
      "product_id": "FG-DWS-00001",
      "kode": "FG-DWS-00001",
      "qty": 200,
      "unit": "PCS",
      "status": "CLOSE",
      "created": "2025-12-30T07:05:03.551Z",
      "notes": ""
    },
    {
      "id": "1767078414922h9y8vylxd0",
      "spkNo": "SPK/251230/8QPPX-A",
      "soNo": "Tes4",
      "customer": "PT. DWIKARYA SEJAHTERA",
      "product": "BOX HI-RIB 677X153X47 (K150/M125/K125 C/F) (SUPPORT HI RIB PRINTING BIRU)",
      "product_id": "FG-DWS-00002",
      "kode": "FG-DWS-00002",
      "qty": 500,
      "unit": "PCS",
      "status": "CLOSE",
      "created": "2025-12-30T07:06:54.922Z",
      "notes": "",
      "originalSpkNo": "SPK/251230/8QPPX",
      "batchNo": "A",
      "stockFulfilled": true,
      "progress": 500
    },
    {
      "id": "1767078414922btvgbfm3f1",
      "spkNo": "SPK/251230/8QPPX-B",
      "soNo": "Tes4",
      "customer": "PT. DWIKARYA SEJAHTERA",
      "product": "BOX HI-RIB 677X153X47 (K150/M125/K125 C/F) (SUPPORT HI RIB PRINTING BIRU)",
      "product_id": "FG-DWS-00002",
      "kode": "FG-DWS-00002",
      "qty": 500,
      "unit": "PCS",
      "status": "CLOSE",
      "created": "2025-12-30T07:06:54.922Z",
      "notes": "",
      "originalSpkNo": "SPK/251230/8QPPX",
      "batchNo": "B"
    },
    {
      "id": "1767078303552qw8mlcxdh",
      "spkNo": "SPK/251230/8QPPX",
      "soNo": "Tes4",
      "customer": "PT. DWIKARYA SEJAHTERA",
      "product": "BOX HI-RIB 677X153X47 (K150/M125/K125 C/F) (SUPPORT HI RIB PRINTING BIRU)",
      "product_id": "FG-DWS-00002",
      "kode": "FG-DWS-00002",
      "qty": 1000,
      "unit": "PCS",
      "status": "OPEN",
      "created": "2025-12-30T07:05:03.552Z",
      "notes": ""
    }
  ],
  "timestamp": 1767078773793,
  "_timestamp": 1767078773793
}